pytest_checkipdb.py
pytest_checkipdb-1.1.1.dist-info/LICENSE
pytest_checkipdb-1.1.1.dist-info/METADATA
pytest_checkipdb-1.1.1.dist-info/WHEEL
pytest_checkipdb-1.1.1.dist-info/entry_points.txt
pytest_checkipdb-1.1.1.dist-info/top_level.txt
pytest_checkipdb-1.1.1.dist-info/RECORD
