Metadata-Version: 2.1
Name: pytest-checkipdb
Version: 1.1.1
Summary: plugin to check if there are ipdb debugs left
Home-page: https://github.com/avallbona/pytest-checkipdb
Author: Andreu Vallbona
Author-email: avallbona@gmail.com
Maintainer: Andreu Vallbona
Maintainer-email: avallbona@gmail.com
License: MIT
Classifier: Development Status :: 5 - Production/Stable
Classifier: Framework :: Pytest
Classifier: Intended Audience :: Developers
Classifier: Topic :: Software Development :: Testing
Classifier: Programming Language :: Python
Classifier: Programming Language :: Python :: 3
Classifier: Programming Language :: Python :: 3.7
Classifier: Programming Language :: Python :: 3.8
Classifier: Programming Language :: Python :: 3.9
Classifier: Programming Language :: Python :: 3.10
Classifier: Programming Language :: Python :: 3.11
Classifier: Programming Language :: Python :: 3.12
Classifier: Programming Language :: Python :: Implementation :: CPython
Classifier: Operating System :: OS Independent
Classifier: License :: OSI Approved :: MIT License
License-File: LICENSE
Requires-Dist: pytest >=2.9.2
